fseconomy/__init__.py
fseconomy/data.py
fseconomy/exceptions.py
fseconomy/response.py
fseconomy/core/__init__.py
fseconomy/core/api.py
fseconomy/core/fetch.py
fseconomy/core/keys.py
fseconomy/core/data/__init__.py
fseconomy/core/data/aircraft.py
fseconomy/core/data/airport.py
fseconomy/core/data/aliases.py
fseconomy/core/data/assignment.py
fseconomy/core/data/commodity.py
fseconomy/core/data/config.py
fseconomy/core/data/facility.py
fseconomy/core/data/fbo.py
fseconomy/core/data/flight.py
fseconomy/core/data/member.py
fseconomy/core/data/status.py
fseconomy/core/data/summary.py
fseconomy/util/__init__.py
fseconomy/util/hex.py
fseconomy/util/time.py
fseconomy/util/xml.py
fseconomy_python-0.1.2.dist-info/METADATA
fseconomy_python-0.1.2.dist-info/WHEEL
fseconomy_python-0.1.2.dist-info/licenses/LICENSE
fseconomy_python-0.1.2.dist-info/RECORD
