Metadata-Version: 2.4
Name: fseconomy-python
Version: 0.1.2
Summary:  Python Bindings for FSEconomy
Project-URL: Homepage, https://github.com/fseconomy/fseconomy-python
Project-URL: Issues, https://github.com/fseconomy/fseconomy-python/issues
Author: Daemotron
License-Expression: MIT
License-File: LICENSE
Classifier: Operating System :: OS Independent
Classifier: Programming Language :: Python :: 3
Requires-Python: >=3.9
Requires-Dist: requests>=2.31.0
